databrief/__init__.py
databrief/py.typed
databrief/utilities.py
databrief/tests/__init__.py
databrief/tests/test_utilities.py
databrief-0.0.2.dist-info/licenses/LICENSE
databrief-0.0.2.dist-info/METADATA
databrief-0.0.2.dist-info/WHEEL
databrief-0.0.2.dist-info/top_level.txt
databrief-0.0.2.dist-info/RECORD
